django_select2_admin_filters/__init__.py
django_select2_admin_filters/admin.py
django_select2_admin_filters/filters.py
django_select2_admin_filters/mixins.py
django_select2_admin_filters/static/select2_admin_filter.css
django_select2_admin_filters/static/select2_admin_filter.js
django_select2_admin_filters/templates/admin/select2_change_list.html
django_select2_admin_filters/templates/admin/select2_change_list_filter_confirm_sidebar.html
django_select2_admin_filters/templates/admin/select2_filter.html
django_select2_admin_filters/templatetags/__init__.py
django_select2_admin_filters/templatetags/select2_filters.py
django_select2_admin_filters-0.1.4.dist-info/LICENSE
django_select2_admin_filters-0.1.4.dist-info/METADATA
django_select2_admin_filters-0.1.4.dist-info/WHEEL
django_select2_admin_filters-0.1.4.dist-info/top_level.txt
django_select2_admin_filters-0.1.4.dist-info/RECORD
