Metadata-Version: 2.1
Name: django-select2-admin-filters
Version: 0.1.4
Summary: A simple extension to Django app to render filters in django admin panel as autocomplete widget.
Home-page: UNKNOWN
Author: Bartłomiej Żmudziński
Author-email: zmudzinski.bartek@gmail.com
License: MIT
Project-URL: Source, https://github.com/the-bit-by-bit/django-select2-admin-filters
Platform: UNKNOWN
Classifier: Environment :: Web Environment
Classifier: Framework :: Django
Classifier: Framework :: Django :: 2.2
Classifier: Framework :: Django :: 3.0
Classifier: Programming Language :: Python
Classifier: Programming Language :: Python :: 3
Classifier: Programming Language :: Python :: 3.5
Classifier: Programming Language :: Python :: 3.6
Classifier: Programming Language :: Python :: 3.7
Classifier: Programming Language :: Python :: 3.8
Classifier: Programming Language :: Python :: 3 :: Only
Classifier: Operating System :: OS Independent
Requires-Python: >=3.5
Requires-Dist: django (>=2.2)
